decorators.py
handy_decorators-0.0.7.dist-info/LICENCE.txt
handy_decorators-0.0.7.dist-info/METADATA
handy_decorators-0.0.7.dist-info/WHEEL
handy_decorators-0.0.7.dist-info/top_level.txt
handy_decorators-0.0.7.dist-info/RECORD
