Metadata-Version: 2.1
Name: handy-decorators
Version: 0.0.7
Summary: Handy decorators for day-to-day use!
Home-page: UNKNOWN
License: UNKNOWN
Platform: UNKNOWN
Requires-Dist: logging
